MANIFEST.in
README.txt
build_info.json
requirements.txt
setup.py
./sidecar/logzio.conf
cs18_sidecar.egg-info/PKG-INFO
cs18_sidecar.egg-info/SOURCES.txt
cs18_sidecar.egg-info/dependency_links.txt
cs18_sidecar.egg-info/entry_points.txt
cs18_sidecar.egg-info/requires.txt
cs18_sidecar.egg-info/top_level.txt
sidecar/__init__.py
sidecar/app_instance_config_status_event_reporter.py
sidecar/app_instance_event_handler.py
sidecar/app_instance_events.py
sidecar/app_instance_identifier.py
sidecar/app_instance_identifier_creator.py
sidecar/app_instance_service.py
sidecar/app_request_info.py
sidecar/app_status_maintainer.py
sidecar/apps_configuration_end_tracker.py
sidecar/aws_app_instance_identifier_creator.py
sidecar/aws_app_instance_service.py
sidecar/aws_error_helper.py
sidecar/aws_instance_states.py
sidecar/aws_sandbox_deployment_end_updater.py
sidecar/aws_sandbox_start_time_updater.py
sidecar/aws_sandbox_terminating_query.py
sidecar/aws_session.py
sidecar/aws_status_maintainer.py
sidecar/aws_status_maintainer_mock.py
sidecar/aws_tag_helper.py
sidecar/configuration_start_policy.py
sidecar/const.py
sidecar/file_system.py
sidecar/filters.py
sidecar/kub_api_pod_reader.py
sidecar/kub_api_service.py
sidecar/kub_app_instance_identifier_creator.py
sidecar/kub_app_instance_service.py
sidecar/kub_sandbox_deployment_end_updater.py
sidecar/kub_sandbox_entity_handler.py
sidecar/kub_sandbox_start_time_updater.py
sidecar/kub_status_maintainer.py
sidecar/kub_token_provider.py
sidecar/messaging_service.py
sidecar/non_blocking_stream_reader.py
sidecar/qualiy_monitor.py
sidecar/request_logger.py
sidecar/sandbox_deployment_end_updater.py
sidecar/sandbox_deployment_state_tracker.py
sidecar/sandbox_end_deployment_notifier.py
sidecar/sandbox_error.py
sidecar/sandbox_start_time_updater.py
sidecar/sandbox_terminating_query.py
sidecar/service_termination_start_policy.py
sidecar/sidecar_api.py
sidecar/status_maintainer.py
sidecar/utils.py
sidecar/app_services/__init__.py
sidecar/app_services/app_service.py
sidecar/azure_clp/__init__.py
sidecar/azure_clp/azure_app_instance_identifier_creator.py
sidecar/azure_clp/azure_app_instance_service.py
sidecar/azure_clp/azure_clients.py
