Metadata-Version: 1.1
Name: cs18-sidecar
Version: 0.0.2.4654
Summary: Sidecar - The CS18 instance
Home-page: UNKNOWN
Author: Quali
Author-email: support@qualisystems.com
License: UNKNOWN
Platform: UNKNOWN
Classifier: Programming Language :: Python :: 3
